kozmoml_catboost/__init__.py
kozmoml_catboost/catboost.py
kozmoml_catboost/version.py
kozmoml_catboost-0.1.0.dev1.dist-info/LICENSE
kozmoml_catboost-0.1.0.dev1.dist-info/METADATA
kozmoml_catboost-0.1.0.dev1.dist-info/WHEEL
kozmoml_catboost-0.1.0.dev1.dist-info/RECORD
