Metadata-Version: 2.1
Name: kozmoml-catboost
Version: 0.1.0.dev1
Summary: Catboost runtime for KozmoML
License: Apache-2.0
Author: KozmoAI
Author-email: developers@kozmoai.io
Maintainer: KozmoAI Ltd.
Maintainer-email: hello@kozmoai.io
Requires-Python: >=3.9,<3.12
Classifier: License :: OSI Approved :: Apache Software License
Classifier: Programming Language :: Python :: 3
Classifier: Programming Language :: Python :: 3.9
Classifier: Programming Language :: Python :: 3.10
Classifier: Programming Language :: Python :: 3.11
Requires-Dist: catboost
Requires-Dist: joblib
Requires-Dist: kozmoml
